License.txt
setup.py
AAIT_MacOS.egg-info/PKG-INFO
AAIT_MacOS.egg-info/SOURCES.txt
AAIT_MacOS.egg-info/dependency_links.txt
AAIT_MacOS.egg-info/entry_points.txt
AAIT_MacOS.egg-info/namespace_packages.txt
AAIT_MacOS.egg-info/requires.txt
AAIT_MacOS.egg-info/top_level.txt
orangecontrib/__init__.py
orangecontrib/AAIT/__init__.py
orangecontrib/AAIT/audit_widget/SignalReceiver.py
orangecontrib/AAIT/audit_widget/__init__.py
orangecontrib/AAIT/audit_widget/audit_widget.py
orangecontrib/AAIT/audit_widget/dynamic_results.py
orangecontrib/AAIT/audit_widget/test_all_widgets.py
orangecontrib/AAIT/audit_widget/test_server.py
orangecontrib/AAIT/audit_widget/widget_4all.py
orangecontrib/AAIT/audit_widget/widget_chunking.py
orangecontrib/AAIT/audit_widget/widget_edit_table.py
orangecontrib/AAIT/audit_widget/widget_mpnet_create_embeddings.py
orangecontrib/AAIT/audit_widget/widget_optimisation.py
orangecontrib/AAIT/audit_widget/widget_optimisationselection.py
orangecontrib/AAIT/audit_widget/widget_powfactory.py
orangecontrib/AAIT/audit_widget/widget_queryllm.py
orangecontrib/AAIT/audit_widget/widget_spacy_md_fr_lemmatizer.py
orangecontrib/AAIT/audit_widget/widget_traduction.py
orangecontrib/AAIT/audit_widget/widgets_model.py
orangecontrib/AAIT/audit_widget/dataTests/00079473A - Copie (2).TIF
orangecontrib/AAIT/audit_widget/dataTests/00079473A - Copie (3).TIF
orangecontrib/AAIT/audit_widget/dataTests/00079473A - Copie (4).TIF
orangecontrib/AAIT/audit_widget/dataTests/Tir 81mm_0001.csv
orangecontrib/AAIT/audit_widget/dataTests/Tir 81mm_0002.csv
orangecontrib/AAIT/audit_widget/dataTests/Tir 81mm_0003.csv
orangecontrib/AAIT/encapsulation/__init__.py
orangecontrib/AAIT/fix_torch/fix_torch_dll_error.py
orangecontrib/AAIT/fix_torch/libomp140.x86_64.dll
orangecontrib/AAIT/llm/GPT4ALL.py
orangecontrib/AAIT/llm/GPT4ALL_killer.py
orangecontrib/AAIT/llm/MergeBaseLora.py
orangecontrib/AAIT/llm/Tutorial_Finetuning.py
orangecontrib/AAIT/llm/Tutorial_TestFinetuning.py
orangecontrib/AAIT/llm/__init__.py
orangecontrib/AAIT/llm/answers.py
orangecontrib/AAIT/llm/chunking.py
orangecontrib/AAIT/llm/embeddings.py
orangecontrib/AAIT/llm/finetuning.py
orangecontrib/AAIT/llm/functions_DatasetGeneration.py
orangecontrib/AAIT/llm/functions_Finetuning.py
