Metadata-Version: 2.1
Name: AAIT-MacOS
Version: 0.0.0.2
Summary: Advanced Artificial Intelligence Tools is a package meant to develop and enable advanced AI functionalities in Orange
Home-page: 
Author: Orange community
Author-email: 
Keywords: orange3 add-on
License-File: License.txt
Requires-Dist: torch==2.2.2
Requires-Dist: sentence-transformers==3.3.1
Requires-Dist: gpt4all==2.8.2
Requires-Dist: sacremoses==0.1.1
Requires-Dist: transformers==4.46.3
Requires-Dist: sentencepiece==0.2.0
Requires-Dist: optuna
Requires-Dist: spacy==3.7.6
Requires-Dist: markdown
Requires-Dist: uvicorn
Requires-Dist: fastapi
Requires-Dist: python-multipart
Requires-Dist: PyMuPDF==1.24.14
Requires-Dist: chonkie==0.4.1
Requires-Dist: GPUtil==1.4.0
Requires-Dist: unidecode==1.3.8
Requires-Dist: python-docx==1.1.2
Requires-Dist: psutil
Requires-Dist: thefuzz==0.22.1
